sets.py
sets_operation_over_files-0.1.1.dist-info/DESCRIPTION.rst
sets_operation_over_files-0.1.1.dist-info/METADATA
sets_operation_over_files-0.1.1.dist-info/RECORD
sets_operation_over_files-0.1.1.dist-info/WHEEL
sets_operation_over_files-0.1.1.dist-info/entry_points.txt
sets_operation_over_files-0.1.1.dist-info/metadata.json
sets_operation_over_files-0.1.1.dist-info/top_level.txt
