Metadata-Version: 2.0
Name: sets-operation-over-files
Version: 0.1.1
Summary: Set operate over files which contains set of lines
Home-page: https://github.com/weaming/sets
Author: weaming
Author-email: garden.yuen@gmail.com
License: UNKNOWN
Project-URL: Bug Reports, https://github.com/weaming/sets
Project-URL: Source, https://github.com/weaming/sets
Keywords: set,cli
Platform: UNKNOWN
